devtools_html_prettifier/__init__.py
devtools_html_prettifier-1.0.1.dist-info/METADATA
devtools_html_prettifier-1.0.1.dist-info/WHEEL
devtools_html_prettifier-1.0.1.dist-info/top_level.txt
devtools_html_prettifier-1.0.1.dist-info/RECORD
