Metadata-Version: 2.1
Name: devtools-html-prettifier
Version: 1.0.1
Summary: HTML prettifier/formatter
Home-page: https://devtools.at/tools/html-prettifier
Author: DevTools.at
Author-email: hello@devtools.at
Project-URL: Homepage, https://devtools.at/tools/html-prettifier
Project-URL: Repository, https://github.com/devtools-at/html-prettifier
Classifier: Development Status :: 4 - Beta
Classifier: Intended Audience :: Developers
Classifier: License :: OSI Approved :: MIT License
Classifier: Programming Language :: Python :: 3
Requires-Python: >=3.8
